opensandbox/__init__.py
opensandbox/constants.py
opensandbox/manager.py
opensandbox/py.typed
opensandbox/sandbox.py
opensandbox/adapters/__init__.py
opensandbox/adapters/command_adapter.py
opensandbox/adapters/factory.py
opensandbox/adapters/filesystem_adapter.py
opensandbox/adapters/health_adapter.py
opensandbox/adapters/metrics_adapter.py
opensandbox/adapters/sandboxes_adapter.py
opensandbox/adapters/converter/__init__.py
opensandbox/adapters/converter/event_node.py
opensandbox/adapters/converter/exception_converter.py
opensandbox/adapters/converter/execution_converter.py
opensandbox/adapters/converter/execution_event_dispatcher.py
opensandbox/adapters/converter/filesystem_model_converter.py
opensandbox/adapters/converter/metrics_model_converter.py
opensandbox/adapters/converter/response_handler.py
opensandbox/adapters/converter/sandbox_model_converter.py
opensandbox/api/__init__.py
opensandbox/api/execd/__init__.py
opensandbox/api/execd/client.py
opensandbox/api/execd/errors.py
opensandbox/api/execd/py.typed
opensandbox/api/execd/types.py
opensandbox/api/execd/api/__init__.py
opensandbox/api/execd/api/code_interpreting/__init__.py
opensandbox/api/execd/api/code_interpreting/create_code_context.py
opensandbox/api/execd/api/code_interpreting/delete_context.py
opensandbox/api/execd/api/code_interpreting/delete_contexts_by_language.py
opensandbox/api/execd/api/code_interpreting/get_context.py
opensandbox/api/execd/api/code_interpreting/interrupt_code.py
opensandbox/api/execd/api/code_interpreting/list_contexts.py
opensandbox/api/execd/api/code_interpreting/run_code.py
opensandbox/api/execd/api/command/__init__.py
opensandbox/api/execd/api/command/get_background_command_logs.py
opensandbox/api/execd/api/command/get_command_status.py
opensandbox/api/execd/api/command/interrupt_command.py
opensandbox/api/execd/api/command/run_command.py
opensandbox/api/execd/api/filesystem/__init__.py
opensandbox/api/execd/api/filesystem/chmod_files.py
opensandbox-0.1.1.dist-info/METADATA
opensandbox-0.1.1.dist-info/WHEEL
opensandbox-0.1.1.dist-info/licenses/LICENSE
opensandbox-0.1.1.dist-info/RECORD
