Metadata-Version: 2.4
Name: opensandbox
Version: 0.1.1
Summary: OpenSandbox Python SDK - Secure, isolated execution environments
Project-URL: Homepage, https://github.com/alibaba/OpenSandbox
Project-URL: Repository, https://github.com/alibaba/OpenSandbox
Project-URL: Documentation, https://docs.opensandbox.io
Project-URL: Issues, https://github.com/alibaba/OpenSandbox/issues
Author-email: OpenSandbox Team <ninan.nn@alibaba-inc.com>
License:                                  Apache License
License-File: LICENSE
Keywords: code-execution,docker,opensandbox,sandbox,sdk,security
Classifier: Development Status :: 3 - Alpha
Classifier: Intended Audience :: Developers
Classifier: License :: OSI Approved :: Apache Software License
Classifier: Operating System :: OS Independent
Classifier: Programming Language :: Python :: 3
Classifier: Programming Language :: Python :: 3 :: Only
Classifier: Programming Language :: Python :: 3.10
Classifier: Programming Language :: Python :: 3.11
Classifier: Programming Language :: Python :: 3.12
Classifier: Programming Language :: Python :: 3.13
Classifier: Topic :: Software Development :: Libraries
Classifier: Typing :: Typed
Requires-Python: >=3.10
Requires-Dist: attrs<25.0,>=21.3.0
Requires-Dist: httpx<1.0,>=0.28.1
Requires-Dist: pydantic<3.0,>=2.4.2
Requires-Dist: python-dateutil<3.0,>=2.8.2
